utilidades_dados/__init__.py
utilidades_dados/operacoes.py
utilidades_dados/tratamento_dados.py
utilidades_dados-0.0.2.dist-info/METADATA
utilidades_dados-0.0.2.dist-info/WHEEL
utilidades_dados-0.0.2.dist-info/top_level.txt
utilidades_dados-0.0.2.dist-info/RECORD
