Metadata-Version: 2.1
Name: utilidades-dados
Version: 0.0.2
Summary: Pacote de cálculos simples e para tratamento de dados.
Home-page: https://github.com/rdaniloc/utilidade-dados-package.git
Author: my_name
Author-email: caiena.danilo@gmail.com
License: UNKNOWN
Platform: UNKNOWN
Requires-Python: >=3.8
Requires-Dist: pandas
Requires-Dist: numpy
